coso/__init__.py
coso/cola_parser.py
coso/configuration.py
coso/count.py
coso/gen_plots.py
coso/launcher.py
coso/level_1.py
coso/level_2.py
coso/logger.py
coso/parsetab.py
coso/problem.py
coso/sharpCSP.py
coso/solver.py
coso/tester.py
coso/util.py
coso/venn.py
coso/viscoso.py
coso/viscoso_widget.py
coso/VisCoSo/__init__.py
coso/VisCoSo/header.html
coso/VisCoSo/viscoso.css
coso/VisCoSo/viscoso.html
coso-1.1.5.dist-info/LICENSE
coso-1.1.5.dist-info/METADATA
coso-1.1.5.dist-info/WHEEL
coso-1.1.5.dist-info/top_level.txt
coso-1.1.5.dist-info/RECORD
