Metadata-Version: 2.1
Name: coso
Version: 1.1.5
Summary: A solver for combinatorics math word problems.
Home-page: https://github.com/PietroTotis/CoSo
Author: Pietro Totis
Author-email: pietro.totis@kuleuven.be
License: GNU General Public License (GPL)
Keywords: combinatorics automated reasoning
Classifier: Development Status :: 4 - Beta
Classifier: Programming Language :: Python :: 3.8
Classifier: Topic :: Scientific/Engineering :: Artificial Intelligence
Classifier: License :: OSI Approved :: GNU General Public License (GPL)
License-File: LICENSE
Requires-Dist: portion
Requires-Dist: clingo (==5.5.1)
Requires-Dist: psutil
Requires-Dist: yattag
Requires-Dist: ply
Requires-Dist: anywidget
